logic_python2sympy/__init__.py
logic_python2sympy/main.py
logic_python2sympy/transformer.py
logic_python2sympy-0.1.3.dist-info/LICENSE
logic_python2sympy-0.1.3.dist-info/METADATA
logic_python2sympy-0.1.3.dist-info/WHEEL
logic_python2sympy-0.1.3.dist-info/RECORD
