Metadata-Version: 2.1
Name: logic-python2sympy
Version: 0.1.3
Summary: convert a logical expression written in `Python` syntax, into a `Sympy` expression
Home-page: https://github.com/duntytelessia/logic_python2sympy/
License: MIT
Keywords: logical expression,sympy
Author: Telessia
Author-email: dunty.telessia@gmail.com
Requires-Python: >=3.12,<4.0
Classifier: License :: OSI Approved :: MIT License
Classifier: Programming Language :: Python :: 3
Classifier: Programming Language :: Python :: 3.12
Requires-Dist: astor (>=0.8.1,<0.9.0)
Requires-Dist: sympy (>=1.13.0,<2.0.0)
Project-URL: Repository, https://github.com/duntytelessia/logic_python2sympy/
